[
  {
    "code": "lysa_hora",
    "peak": "Lysá hora",
    "time": "20.11.2025 15:00",
    "temperature": -3.4,
    "humidity": 96.0,
    "wind": 4.0,
    "wind_gust": 9.0,
    "details": "mlha v poslední hodině"
  },
  {
    "code": "pustevny",
    "peak": "Pustevny",
    "time": "20.11.2025 14:30",
    "temperature": -0.5,
    "humidity": 96.0
  },
  {
    "code": "velky_javornik",
    "peak": "Velký Javorník",
    "time": "20.11.2025 14:30",
    "temperature": 0.0,
    "precipitation": 0.0
  }
]