[
  {
    "code": "lysa_hora",
    "peak": "Lysá hora",
    "time": "11.02.2026 09:00",
    "temperature": -3.2,
    "humidity": 94.0,
    "wind": 13.0,
    "wind_gust": 17.8,
    "details": "mlha mrznoucí, oblohu nelze rozeznat"
  },
  {
    "code": "pustevny",
    "peak": "Pustevny",
    "time": "11.02.2026 10:10",
    "temperature": -0.8,
    "humidity": 100.0
  },
  {
    "code": "velky_javornik",
    "peak": "Velký Javorník",
    "time": "11.02.2026 09:40",
    "temperature": -1.0,
    "precipitation": 0.0
  }
]