[
  {
    "code": "lysa_hora",
    "peak": "Lysá hora",
    "time": "14.07.2025 13:00",
    "temperature": 21.2,
    "humidity": 61.0,
    "wind": 2.0,
    "wind_gust": 4.9,
    "details": "srážky v dohledu dále než 5 km"
  },
  {
    "code": "pustevny",
    "peak": "Pustevny",
    "time": "14.07.2025 13:20",
    "temperature": 24.2,
    "humidity": 65.0
  },
  {
    "code": "velky_javornik",
    "peak": "Velký Javorník",
    "time": "14.07.2025 13:10",
    "temperature": 24.0,
    "precipitation": 0.0
  }
]