[
  {
    "code": "lysa_hora",
    "peak": "Lysá hora",
    "time": "23.11.2025 07:00",
    "temperature": -8.8,
    "humidity": 91.0,
    "wind": 6.0,
    "wind_gust": 10.7,
    "details": "sněžení mírné trvalé"
  },
  {
    "code": "pustevny",
    "peak": "Pustevny",
    "time": "23.11.2025 07:10",
    "temperature": -6.6,
    "humidity": 99.1
  },
  {
    "code": "velky_javornik",
    "peak": "Velký Javorník",
    "time": "23.11.2025 06:40",
    "temperature": -7.0,
    "precipitation": 0.0
  }
]