[
  {
    "code": "lysa_hora",
    "peak": "Lysá hora",
    "time": "17.05.2025 10:00",
    "temperature": 0.6,
    "humidity": 97.0,
    "wind": 7.0,
    "wind_gust": 10.4,
    "details": "mlha beze změny, oblohu nelze rozeznat"
  },
  {
    "code": "pustevny",
    "peak": "Pustevny",
    "time": "17.05.2025 10:30",
    "temperature": 5.0,
    "humidity": 97.4
  },
  {
    "code": "velky_javornik",
    "peak": "Velký Javorník",
    "time": "17.05.2025 10:10",
    "temperature": 6.0,
    "precipitation": 0.0
  }
]