[
  {
    "code": "lysa_hora",
    "peak": "Lysá hora",
    "time": "09.12.2025 14:00",
    "temperature": 4.7,
    "humidity": 97.0,
    "wind": 8.0,
    "wind_gust": 13.5,
    "details": "mlha v chuchvalcích"
  },
  {
    "code": "pustevny",
    "peak": "Pustevny",
    "time": "09.12.2025 15:10",
    "temperature": 6.4,
    "humidity": 100.0
  },
  {
    "code": "velky_javornik",
    "peak": "Velký Javorník",
    "time": "09.12.2025 15:00",
    "temperature": 6.0,
    "precipitation": 0.0
  }
]