[
  {
    "code": "lysa_hora",
    "peak": "Lysá hora",
    "time": "22.11.2025 08:00",
    "temperature": -8.2,
    "humidity": 92.0,
    "wind": 8.0,
    "wind_gust": 12.5,
    "details": "mlha mrznoucí, oblohu nelze rozeznat"
  },
  {
    "code": "pustevny",
    "peak": "Pustevny",
    "time": "22.11.2025 07:50",
    "temperature": -5.8,
    "humidity": 99.6
  },
  {
    "code": "velky_javornik",
    "peak": "Velký Javorník",
    "time": "22.11.2025 07:30",
    "temperature": -6.0,
    "precipitation": 0.0
  }
]